LICENSE
MANIFEST.in
README.md
setup.cfg
setup.py
DoCodeDB/__init__.py
DoCodeDB/admin.py
DoCodeDB/apps.py
DoCodeDB/models.py
DoCodeDB/urls.py
DoCodeDB/views.py
DoCodeDB/migrations/__init__.py
DoCodeDB/migrations/__pycache__/__init__.cpython-37.pyc
DoCodeDB/procesos/correo_sendGrid.py
DoCodeDB/procesos/dc_form.py
DoCodeDB/procesos/__pycache__/correo_sendGrid.cpython-37.pyc
DoCodeDB/procesos/__pycache__/dc_form.cpython-37.pyc
DoCodeDB/static/font-awesome-4.7.0/HELP-US-OUT.txt
DoCodeDB/static/font-awesome-4.7.0/css/font-awesome.css
DoCodeDB/static/font-awesome-4.7.0/css/font-awesome.min.css
DoCodeDB/static/font-awesome-4.7.0/fonts/FontAwesome.otf
DoCodeDB/static/font-awesome-4.7.0/fonts/fontawesome-webfont.eot
DoCodeDB/static/font-awesome-4.7.0/fonts/fontawesome-webfont.svg
DoCodeDB/static/font-awesome-4.7.0/fonts/fontawesome-webfont.ttf
DoCodeDB/static/font-awesome-4.7.0/fonts/fontawesome-webfont.woff
DoCodeDB/static/font-awesome-4.7.0/fonts/fontawesome-webfont.woff2
DoCodeDB/static/font-awesome-4.7.0/less/animated.less
DoCodeDB/static/font-awesome-4.7.0/less/bordered-pulled.less
DoCodeDB/static/font-awesome-4.7.0/less/core.less
DoCodeDB/static/font-awesome-4.7.0/less/fixed-width.less
DoCodeDB/static/font-awesome-4.7.0/less/font-awesome.less
DoCodeDB/static/font-awesome-4.7.0/less/icons.less
DoCodeDB/static/font-awesome-4.7.0/less/larger.less
DoCodeDB/static/font-awesome-4.7.0/less/list.less
DoCodeDB/static/font-awesome-4.7.0/less/mixins.less
DoCodeDB/static/font-awesome-4.7.0/less/path.less
DoCodeDB/static/font-awesome-4.7.0/less/rotated-flipped.less
DoCodeDB/static/font-awesome-4.7.0/less/screen-reader.less
DoCodeDB/static/font-awesome-4.7.0/less/stacked.less
DoCodeDB/static/font-awesome-4.7.0/less/variables.less
DoCodeDB/static/font-awesome-4.7.0/scss/_animated.scss
DoCodeDB/static/font-awesome-4.7.0/scss/_bordered-pulled.scss
DoCodeDB/static/font-awesome-4.7.0/scss/_core.scss
DoCodeDB/static/font-awesome-4.7.0/scss/_fixed-width.scss
dj_DoCodeDB.egg-info/PKG-INFO
dj_DoCodeDB.egg-info/SOURCES.txt
dj_DoCodeDB.egg-info/dependency_links.txt
dj_DoCodeDB.egg-info/top_level.txt