Metadata-Version: 2.1
Name: dj-DoCodeDB
Version: 2.0.3
Summary: Manage DataBase Models Easy.
Home-page: https://www.docode.com.mx/
Author: DoCode
Author-email: mario@docode.com.mx,elias@docode.com.mx
License: MIT
Platform: UNKNOWN
Classifier: Environment :: Web Environment
Classifier: Framework :: Django
Classifier: Intended Audience :: Developers
Classifier: License :: OSI Approved :: BSD License
Classifier: Operating System :: OS Independent
Classifier: Programming Language :: Python
Classifier: Topic :: Internet :: WWW/HTTP
